dag_vis/__init__.py
dag_vis/dag_vis.py
parsl_dag_vis-0.1.6.dist-info/DESCRIPTION.rst
parsl_dag_vis-0.1.6.dist-info/METADATA
parsl_dag_vis-0.1.6.dist-info/RECORD
parsl_dag_vis-0.1.6.dist-info/WHEEL
parsl_dag_vis-0.1.6.dist-info/metadata.json
parsl_dag_vis-0.1.6.dist-info/top_level.txt
