Metadata-Version: 2.0
Name: parsl-dag-vis
Version: 0.1.6
Summary: DAG visualization code to be run from Jupyter notebooks to visualize data flow dependency graphs of workflows
Home-page: https://github.com/benhg/parsl-dag-vis
Author: Ben Glick
Author-email: glick@lclark.edu
License: Apache 2.0
Download-URL: https://github.com/benhg/parsl-dag-vis/archive/v0.1-alpha.zip
Keywords: parsl,jupyter,visualization,Workflows,Scientific computing
Platform: UNKNOWN
Classifier: Development Status :: 3 - Alpha
Classifier: License :: OSI Approved :: Apache Software License
Classifier: Intended Audience :: Developers
Classifier: Programming Language :: Python :: 3.5
Classifier: Programming Language :: Python :: 3.6
Requires-Dist: parsl
Requires-Dist: jupyter
Requires-Dist: ipython
